CHANGELOG.md
MANIFEST.in
README.md
requirements.txt
setup.py
pymongodm/__init__.py
pymongodm.egg-info/PKG-INFO
pymongodm.egg-info/SOURCES.txt
pymongodm.egg-info/dependency_links.txt
pymongodm.egg-info/not-zip-safe
pymongodm.egg-info/requires.txt
pymongodm.egg-info/top_level.txt
pymongodm/models/__init__.py
pymongodm/models/plugins/__init__.py
pymongodm/models/plugins/validation.py
pymongodm/utils/__init__.py