Metadata-Version: 1.1
Name: pymongodm
Version: 2.0.6
Summary: pymongodm
Home-page: https://github.com/GlobalStudioES/pymongodm
Author: GlobalStudio
Author-email: contacto@globalstudio.es
License: GPL
Keywords: globalstudio,odm,mongo,pymongo
Platform: UNKNOWN
Classifier: Development Status :: 4 - Beta
Classifier: Programming Language :: Python :: 2
Classifier: Programming Language :: Python :: 3
